correlationinspector/__init__.py
correlationinspector/correlation_analysis.py
correlationinspector/utils.py
correlationinspector-0.1.0.dist-info/LICENSE
correlationinspector-0.1.0.dist-info/METADATA
correlationinspector-0.1.0.dist-info/WHEEL
correlationinspector-0.1.0.dist-info/top_level.txt
correlationinspector-0.1.0.dist-info/RECORD
